<Taems>
	<Task id="A1T1" name="PickPatient4" qaf="SeqSum" >
		<Method id="A1M1T1" name="PickFromHouse4" Quality="500" Duration="10" XCoord="100" YCoord="450"></Method>
		<Method id="A1M2T1" name="DropToHospital4" Quality="500" Duration="10" XCoord="100" YCoord="500"></Method>
	</Task>
	<Task id="A1T2" name="DropPatient4" qaf="SeqSum" >
		<Method id="A1M1T2" name="PickFromHospital4" Quality="500" Duration="10" XCoord="300" YCoord="450"></Method>
		<Method id="A1M2T2" name="DropToHouse4" Quality="500" Duration="10" XCoord="300" YCoord="500"></Method>
	</Task>
	<Task id="T3" name="RespondToAccident" qaf="SumAll" >
		<Method id="A1M1T3" name="VisitAccidentLocation" Quality="200" Duration="10" XCoord="400" YCoord="250"></Method>
		</Task>
	<Task id="T6" name="RespondToAccident2" qaf="SumAll" >
		<Method id="A2M6T5" name="VisitAccidentLocation2" Quality="200" Duration="10" XCoord="400" YCoord="350"></Method>
	</Task>
		<Task id="T7" name="RespondToAccident3" qaf="SumAll" >
		<Method id="A2M6T5" name="VisitAccidentLocation3" Quality="200" Duration="10" XCoord="400" YCoord="450"></Method>
	</Task>
		<Task id="T8" name="RespondToAccident4" qaf="SumAll" >
		<Method id="A2M6T5" name="VisitAccidentLocation4" Quality="200" Duration="10" XCoord="400" YCoord="550"></Method>
	</Task>
		<Task id="T9" name="RespondToAccident5" qaf="SumAll" >
		<Method id="A2M6T5" name="VisitAccidentLocation5" Quality="200" Duration="10" XCoord="400" YCoord="650"></Method>
	</Task>
		<Task id="T10" name="RespondToAccident6" qaf="SumAll" >
		<Method id="A2M6T5" name="VisitAccidentLocation6" Quality="200" Duration="10" XCoord="400" YCoord="750"></Method>
	</Task>
		<Task id="T11" name="RespondToAccident7" qaf="SumAll" >
		<Method id="A2M6T5" name="VisitAccidentLocation7" Quality="200" Duration="10" XCoord="400" YCoord="850"></Method>
	</Task>
		<Task id="T12" name="RespondToAccident8" qaf="SumAll" >
		<Method id="A2M6T5" name="VisitAccidentLocation8" Quality="200" Duration="10" XCoord="400" YCoord="950"></Method>
	</Task>
		<Task id="T13" name="RespondToAccident9" qaf="SumAll" >
		<Method id="A2M6T5" name="VisitAccidentLocation9" Quality="200" Duration="10" XCoord="400" YCoord="1050"></Method>
	</Task>
		<Task id="T14" name="RespondToAccident10" qaf="SumAll" >
		<Method id="A2M6T5" name="VisitAccidentLocation10" Quality="200" Duration="10" XCoord="400" YCoord="1150"></Method>
	</Task>
</Taems>